labelme2yolo9/__about__.py
labelme2yolo9/__init__.py
labelme2yolo9/__main__.py
labelme2yolo9/l2y.py
labelme2yolo9/cli/__init__.py
Labelme2YOLO9-0.2.dist-info/METADATA
Labelme2YOLO9-0.2.dist-info/WHEEL
Labelme2YOLO9-0.2.dist-info/top_level.txt
Labelme2YOLO9-0.2.dist-info/RECORD
