Metadata-Version: 2.1
Name: Labelme2YOLO9
Version: 0.2
Summary: Labelme2YOLO9 is a powerful tool for converting LabelMe's JSON dataset to YOLO9  format.
Home-page: https://github.com/Ashwin2929/labelme2yolo9
Author: Ashwin, Purushothamadhas
Author-email: p.ashwin79@gmail.com
Classifier: Programming Language :: Python :: 3.6
Classifier: Programming Language :: Python :: 3.7
Classifier: Programming Language :: Python :: 3.8
Classifier: Programming Language :: Python :: 3.9
Requires-Dist: opencv-python
Requires-Dist: Pillow
Requires-Dist: numpy
Requires-Dist: tqdm
